COPYING
MANIFEST.in
README.rst
bootstrap-buildout.py
buildout.cfg
environment.yml
requirements.txt
setup.py
version.txt
bob/__init__.py
bob.paper.biosig2017_3dmaskprestudy.egg-info/PKG-INFO
bob.paper.biosig2017_3dmaskprestudy.egg-info/SOURCES.txt
bob.paper.biosig2017_3dmaskprestudy.egg-info/dependency_links.txt
bob.paper.biosig2017_3dmaskprestudy.egg-info/entry_points.txt
bob.paper.biosig2017_3dmaskprestudy.egg-info/requires.txt
bob.paper.biosig2017_3dmaskprestudy.egg-info/top_level.txt
bob/paper/__init__.py
bob/paper/biosig2017_3dmaskprestudy/__init__.py
bob/paper/biosig2017_3dmaskprestudy/scripts/__init__.py
bob/paper/biosig2017_3dmaskprestudy/scripts/thermal_mean_hist.py
doc/conf.py
doc/index.rst