Metadata-Version: 1.1
Name: bob.paper.biosig2017-3dmaskprestudy
Version: 1.0.0
Summary: Package for BioSIG-2017 paper on Extended-Range imaging for 3D-Mask PAD.
Home-page: https://gitlab.idiap.ch/bob/bob.paper.biosig2017_3dmaskprestudy
Author: Sushil Bhattacharjee
Author-email: sushil.bhattacharjee@idiap.ch
License: GPLv3
Keywords: Package for BioSIG-2017 paper on Extended-Range imaging for 3D-Mask PAD
Platform: UNKNOWN
Classifier: Framework :: Bob
Classifier: Development Status :: 3 - Alpha
Classifier: Intended Audience :: Developers
Classifier: License :: OSI Approved :: GNU General Public License v3 (GPLv3)
Classifier: Natural Language :: English
Classifier: Programming Language :: Python
Classifier: Topic :: Scientific/Engineering :: Artificial Intelligence
